Metadata-Version: 2.1
Name: replitkey
Version: 1.0
Summary: ReplitKey can get database values from a repl project
Author: mas6y6
